{
  "lesson_id": "el-nuevo-frances-sin-esfuerzo-l013",
  "source": "el-nuevo-frances-sin-esfuerzo",
  "lesson": 13,
  "title": "La belle musique",
  "target_lang": "fr",
  "base_lang": "es",
  "cefr": "A1",
  "audio": "corpus/Assimil - El Nuevo Francés sin Esfuerzo/Audio/13 Leçon 13.mp3",
  "themes": [
    "music",
    "opinions"
  ],
  "lines": [
    {
      "line": 1,
      "target": "-Est-ce que vous aimez cette chanteuse 1) ?",
      "base": "¿Le gusta esta cantante ? :"
    },
    {
      "line": 2,
      "target": "-Bof , elle a une assez belle voix. . .",
      "base": "¡Bah!tiene una voz bastante buena ..."
    },
    {
      "line": 3,
      "target": "mais je trouve que ses chansons sont idiotes ;",
      "base": "pero me parece que sus canciones son ridículas (idiotas) ;",
      "pronunciation": ".. sé xansón' sontidiot'"
    },
    {
      "line": 4,
      "target": "les paroles sont bêtes et la musique est triste.",
      "base": "la letra (palabras) es tonta y la música es triste.",
      "pronunciation": "pajol'... bèt"
    },
    {
      "line": 5,
      "target": "De toute façon , j'aime seulement la musique classique.",
      "base": "De todas formas, me gusta solamente la música clásica.",
      "pronunciation": "dé tut' fasôn ... sélmán...clasik"
    },
    {
      "line": 6,
      "target": "-Vous n'aimez pas du tout la musique moderne ?",
      "base": "¿ No le gusta en absoluto la música moderna ?"
    },
    {
      "line": 7,
      "target": "-Si, mais seulement quand les chansons sont intelligentes et belles.",
      "base": "Sí, pero solamente cuando las canciones son buenas (inteligentes) y bonitas.",
      "pronunciation": ".. sontenteliyant’"
    },
    {
      "line": 8,
      "target": "-Qui aimez-vous par exemple ? -J'aime bien Coco et les Clowns .",
      "base": "¿ Quién le gusta, por ejemplo ? - Me gusta Coco y los Clowns.",
      "pronunciation": "eleclun'"
    },
    {
      "line": 9,
      "target": "Une affiche dans la vitrine d'un magasin :",
      "base": "Un cartel en el escaparate (vitrina) de una tienda :"
    },
    {
      "line": 10,
      "target": "\"Nous cherchons un vendeur : jeune ou vieux ; plein temps ou temps partiel ; expérimenté ou débutant”.",
      "base": "“Se busca(buscamos) vendedor : joven o viejo ; jornada completa (tiempo completo) o media jornada (tiempo parcial) ; con o sin experiencia (experimentado o principiante).",
      "pronunciation": "... afich dan vin dén magazén"
    },
    {
      "line": 11,
      "target": "Et, en-dessous, au crayon : “Mort ou vivant”.",
      "base": "Y, debajo, a lápiz : “Vivo o muerto”.",
      "pronunciation": ".. énd'suo creyón : mor u viván"
    }
  ],
  "gap_candidates": [
    {
      "line": 1,
      "target": "-Est-ce que vous aimez cette chanteuse 1) ?",
      "reasons": [
        "vocab:chanteuse"
      ]
    },
    {
      "line": 2,
      "target": "-Bof (2), elle a une assez belle voix. . .",
      "reasons": [
        "answer_to_question",
        "vocab:voix"
      ]
    },
    {
      "line": 3,
      "target": "mais je trouve que ses chansons sont idiotes (3) ;",
      "reasons": [
        "vocab:idiote"
      ]
    },
    {
      "line": 4,
      "target": "les paroles (4) sont bétes et la musique est triste.",
      "reasons": [
        "vocab:paroles"
      ]
    },
    {
      "line": 5,
      "target": "De toute façon (5), j'aime (6) seulement la musique classique.",
      "reasons": [
        "vocab:classique"
      ]
    },
    {
      "line": 6,
      "target": "-Vous n'aimez pas du tout (7) la musique moderne ?",
      "reasons": [
        "vocab:moderne"
      ]
    },
    {
      "line": 7,
      "target": "-Si, mais seulement quand les chansons sont intelligentes et belles.",
      "reasons": [
        "answer_to_question",
        "vocab:chanson"
      ]
    },
    {
      "line": 9,
      "target": "Une affiche dans la vitrine d'un magasin :",
      "reasons": [
        "answer_to_question",
        "short_response"
      ]
    },
    {
      "line": 10,
      "target": "\"Nous cherchons un vendeur (1) : jeune ou vieux ; plein temps ou temps partiel ; expérimenté ou débutant”.",
      "reasons": [
        "vocab:expérimenté"
      ]
    },
    {
      "line": 11,
      "target": "Et, en-dessous, au crayon : “Mort ou vivant”.",
      "reasons": [
        "short_response",
        "vocab:vivant"
      ]
    }
  ],
  "vocab_introduced": [
    "chanteuse",
    "voix",
    "chanson",
    "idiote",
    "paroles",
    "fr1-bête",
    "triste",
    "classique",
    "moderne",
    "vendeur",
    "vieux",
    "fr1-expérimenté",
    "vivant"
  ]
}
