{
  "lesson_id": "ingles-perfeccionamiento-l008",
  "source": "ingles-perfeccionamiento",
  "lesson": 8,
  "title": "\\\"This happy breed of men, this little world...\\",
  "target_lang": "en",
  "base_lang": "es",
  "cefr": "B2",
  "audio": "Resources/Assimil - Ingles Perfeccionamiento/Audio/08 Lesson 08.mp3",
  "themes": [
    "history",
    "language-evolution",
    "british-culture",
    "norman-influence"
  ],
  "lines": [
    {
      "line": 1,
      "target": "And here is the weather forecast. The",
      "base": "Y aquí está la predicción meteorológica. El Conti-"
    },
    {
      "line": 2,
      "target": "This sentence is more than just a slip of",
      "base": "Esta frase es más que un simple lapsus: la natu-"
    },
    {
      "line": 3,
      "target": "has always played an important part in",
      "base": "ha jugado siempre un papel importante en el de-"
    },
    {
      "line": 4,
      "target": "In the last thousand years — as every",
      "base": "Durante los últimos mil años — dato conocido por"
    },
    {
      "line": 5,
      "target": "When the Normans arrived in 1066, their",
      "base": "Cuando los Normandos llegaron en 1066, su lengua"
    },
    {
      "line": 6,
      "target": "and, for two centuries, French was the",
      "base": "y, durante dos siglos, el francés fue el idioma"
    },
    {
      "line": 7,
      "target": "This influence can still be found today in",
      "base": "Esta influencia puede encontrarse todavía hoy día"
    },
    {
      "line": 8,
      "target": "The peasants tended their sheep, pigs",
      "base": "Los siervos atendían a sus ovejas, cerdos y"
    },
    {
      "line": 9,
      "target": "the meats were called mutton, pork and",
      "base": "las carnes recibían los nombres de mutton, pork y"
    },
    {
      "line": 10,
      "target": "The lord would sit in an elegant « chair »",
      "base": "El señor se sentaba en una «silla» elegante mien-"
    },
    {
      "line": 11,
      "target": "Today, words of Latin origin form the",
      "base": "Hoy día, las palabras de origen latino forman parte"
    },
    {
      "line": 12,
      "target": "but the five thousand words of Old En-",
      "base": "pero las cinco mil palabras del viejo inglés que"
    },
    {
      "line": 13,
      "target": "No wonder the English vocabulary",
      "base": "¡No es para sorprenderse que el vocabulario del"
    },
    {
      "line": 14,
      "target": "But don't worry! According to linguists,",
      "base": "iPero no se preocupe! De acuerdo con los lin-"
    },
    {
      "line": 15,
      "target": "Despite the Channel Tunnel, the British",
      "base": "A pesar del túnel del Canal de la Mancha, los"
    },
    {
      "line": 16,
      "target": "even though their language has borro-",
      "base": "aunque su lengua ha tomado prestado e incorpo-"
    },
    {
      "line": 17,
      "target": "A crusty old Peer of the House of Lords",
      "base": "Un viejo y ceñudo Par de la Cámara de los Lores"
    },
    {
      "line": 18,
      "target": "So you see, | was born English, I've",
      "base": "Pues como ve, nací inglés, siempre he vivido en"
    },
    {
      "line": 19,
      "target": "It's not nationalism, dear fellow, it's just",
      "base": "Esto no es nacionalismo, mi querido amigo, es"
    },
    {
      "line": 20,
      "target": "| see, rejoined the other, but do you have",
      "base": "Ya veo, respondió el otro, ¿pero no tienen ustedes"
    }
  ],
  "gap_candidates": [
    {
      "line": 3,
      "target": "has always played an important part in",
      "reasons": [
        "short_response"
      ]
    },
    {
      "line": 4,
      "target": "In the last thousand years — as every",
      "reasons": [
        "short_response"
      ]
    },
    {
      "line": 5,
      "target": "When the Normans arrived in 1066, their",
      "reasons": [
        "short_response",
        "vocab:norman"
      ]
    },
    {
      "line": 6,
      "target": "and, for two centuries, French was the",
      "reasons": [
        "answer_to_question",
        "short_response"
      ]
    },
    {
      "line": 7,
      "target": "This influence can still be found today in",
      "reasons": [
        "short_response"
      ]
    },
    {
      "line": 8,
      "target": "The peasants tended their sheep, pigs",
      "reasons": [
        "short_response",
        "vocab:sheep"
      ]
    },
    {
      "line": 9,
      "target": "the meats were called mutton, pork and",
      "reasons": [
        "short_response",
        "vocab:mutton"
      ]
    },
    {
      "line": 10,
      "target": "The lord would sit in an elegant « chair »",
      "reasons": [
        "vocab:chair"
      ]
    },
    {
      "line": 11,
      "target": "Today, words of Latin origin form the",
      "reasons": [
        "short_response"
      ]
    },
    {
      "line": 12,
      "target": "but the five thousand words of Old En-",
      "reasons": [
        "short_response"
      ]
    },
    {
      "line": 13,
      "target": "No wonder the English vocabulary",
      "reasons": [
        "short_response"
      ]
    },
    {
      "line": 14,
      "target": "But don't worry! According to linguists,",
      "reasons": [
        "short_response"
      ]
    },
    {
      "line": 15,
      "target": "Despite the Channel Tunnel, the British",
      "reasons": [
        "short_response"
      ]
    },
    {
      "line": 16,
      "target": "even though their language has borro-",
      "reasons": [
        "short_response"
      ]
    },
    {
      "line": 17,
      "target": "A crusty old Peer of the House of Lords",
      "reasons": [
        "vocab:crust"
      ]
    },
    {
      "line": 18,
      "target": "So you see, | was born English, I've",
      "reasons": [
        "short_response"
      ]
    },
    {
      "line": 19,
      "target": "It's not nationalism, dear fellow, it's just",
      "reasons": [
        "short_response"
      ]
    }
  ],
  "vocab_introduced": [
    "enp1ai-cut-off",
    "enp1ai-slip-of-the-tongue",
    "enp1ai-norman",
    "enp1ai-sheep",
    "enp1ai-ox",
    "enp1ai-oxen",
    "enp1ai-mutton",
    "enp1ai-pork",
    "enp1ai-beef",
    "enp1ai-chair",
    "enp1ai-stool",
    "enp1ai-peer",
    "enp1ai-insularity",
    "enp1ai-crusty",
    "enp1ai-crust"
  ]
}